sectionFiberDivide/__init__.py
sectionFiberDivide/fiberGenerate.py
sectionFiberDivide/gmsh.exe
sectionFiberDivide/pointInPolygon.py
sectionFiberDivide/sectionFiberMain.py
sectionFiberDivide/test.py
sectionFiberDivide-1.0.4.dist-info/METADATA
sectionFiberDivide-1.0.4.dist-info/WHEEL
sectionFiberDivide-1.0.4.dist-info/top_level.txt
sectionFiberDivide-1.0.4.dist-info/RECORD
